inference_provider/__init__.py
inference_provider/auth.py
inference_provider/client.py
inference_provider/errors.py
inference_provider/http_client.py
inference_provider/resources/__init__.py
inference_provider/resources/agents.py
inference_provider/resources/base.py
inference_provider/resources/custom_responses.py
inference_provider/resources/mcp_servers.py
inference_provider/resources/providers.py
inference_provider/resources/rag.py
inference_provider/resources/tools.py
inference_provider/types.py
inference_provider/utils.py
inference_provider_sdk-1.0.0.dist-info/METADATA
inference_provider_sdk-1.0.0.dist-info/WHEEL
inference_provider_sdk-1.0.0.dist-info/licenses/LICENSE
inference_provider_sdk-1.0.0.dist-info/RECORD
