Metadata-Version: 2.4
Name: inference-provider-sdk
Version: 1.0.0
Summary: Python SDK for Inference Provider API - Build powerful AI agents with RAG, tool calling, and MCP integration
License: MIT
License-File: LICENSE
Keywords: inference,ai,api,sdk,agent,rag,mcp,llm,chatbot,openai,anthropic,langchain
Author: DevMayur
Author-email: mayurkakade@gmail.com
Requires-Python: >=3.8,<4.0
Classifier: Development Status :: 5 - Production/Stable
Classifier: Intended Audience :: Developers
Classifier: License :: OSI Approved :: MIT License
Classifier: Programming Language :: Python :: 3
Classifier: Programming Language :: Python :: 3.8
Classifier: Programming Language :: Python :: 3.9
Classifier: Programming Language :: Python :: 3.10
Classifier: Programming Language :: Python :: 3.11
Classifier: Programming Language :: Python :: 3.12
Classifier: Programming Language :: Python :: 3.13
Classifier: Programming Language :: Python :: 3.14
Classifier: Topic :: Software Development :: Libraries :: Python Modules
Requires-Dist: httpx (>=0.25.0,<0.26.0)
Requires-Dist: pydantic (>=2.0.0,<3.0.0)
Project-URL: Documentation, https://github.com/DevMayur/Inference_Provider_V2/tree/main/sdks/python
Project-URL: Homepage, https://github.com/DevMayur/Inference_Provider_V2
Project-URL: Repository, https://github.com/DevMayur/Inference_Provider_V2
